ollama_mcpo_adapter/__init__.py
ollama_mcpo_adapter/adapter.py
ollama_mcpo_adapter/cli.py
ollama_mcpo_adapter/config_parser.py
ollama_mcpo_adapter/dispatcher.py
ollama_mcpo_adapter/service.py
ollama_mcpo_adapter/service_runner.py
ollama_mcpo_adapter-0.1.0.dist-info/METADATA
ollama_mcpo_adapter-0.1.0.dist-info/WHEEL
ollama_mcpo_adapter-0.1.0.dist-info/entry_points.txt
ollama_mcpo_adapter-0.1.0.dist-info/licenses/LICENSE
ollama_mcpo_adapter-0.1.0.dist-info/RECORD
