Metadata-Version: 2.4
Name: ollama-mcpo-adapter
Version: 0.1.0
Summary: Adapter to expose MCPO tools in Ollama-compatible format
License-File: LICENSE
Requires-Python: >=3.11
Requires-Dist: mcpo>=0.0.9
Requires-Dist: ollama>=0.4.7
Requires-Dist: psutil>=7.0.0
